samlib/__init__.py
samlib/__version__.py
samlib/_ssc.py
samlib/_ssc.pyi
samlib/_ssc_cffi.pyd
samlib/_ssc_cffi.pyi
samlib/_util.py
samlib/py.typed
samlib/ssc.dll
samlib/ssc.py
samlib/modules/_6parsolve.pyi
samlib/modules/__init__.py
samlib/modules/_types.pyi
samlib/modules/battery.pyi
samlib/modules/battery_stateful.pyi
samlib/modules/battwatts.pyi
samlib/modules/belpe.pyi
samlib/modules/biomass.pyi
samlib/modules/cashloan.pyi
samlib/modules/cashloan_heat.pyi
samlib/modules/cb_construction_financing.pyi
samlib/modules/cb_empirical_hce_heat_loss.pyi
samlib/modules/cb_mspt_system_costs.pyi
samlib/modules/communitysolar.pyi
samlib/modules/csp_dsg_lf_ui.pyi
samlib/modules/csp_subcomponent.pyi
samlib/modules/custom_generation.pyi
samlib/modules/equpartflip.pyi
samlib/modules/etes_electric_resistance.pyi
samlib/modules/etes_ptes.pyi
samlib/modules/fresnel_physical.pyi
samlib/modules/fresnel_physical_iph.pyi
samlib/modules/fuelcell.pyi
samlib/modules/geothermal.pyi
samlib/modules/geothermal_costs.pyi
samlib/modules/grid.pyi
samlib/modules/hcpv.pyi
samlib/modules/host_developer.pyi
samlib/modules/hybrid.pyi
samlib/modules/hybrid_steps.pyi
samlib/modules/iec61853interp.pyi
samlib/modules/iec61853par.pyi
samlib/modules/inv_cec_cg.pyi
samlib/modules/iph_to_lcoefcr.pyi
samlib/modules/ippppa.pyi
samlib/modules/irradproc.pyi
samlib/modules/layoutarea.pyi
samlib/modules/lcoefcr.pyi
samlib/modules/lcoefcr_design.pyi
samlib/modules/levpartflip.pyi
samlib/modules/linear_fresnel_dsg_iph.pyi
samlib/modules/merchantplant.pyi
samlib/modules/mhk_costs.pyi
samlib/modules/mhk_tidal.pyi
samlib/modules/mhk_wave.pyi
samlib/modules/mspt_iph.pyi
samlib/modules/mspt_sf_and_rec_isolated.pyi
samlib/modules/ptes_design_point.pyi
samlib/modules/pv6parmod.pyi
samlib/modules/pv_get_shade_loss_mpp.pyi
samlib/modules/pvsamv1.pyi
samlib/modules/pvsandiainv.pyi
samlib/modules/pvwattsv5.pyi
samlib/modules/pvwattsv5_1ts.pyi
samlib/modules/pvwattsv7.pyi
samlib/modules/pvwattsv8.pyi
samlib-1.298.2.dist-info/METADATA
samlib-1.298.2.dist-info/WHEEL
samlib-1.298.2.dist-info/licenses/LICENSE
samlib-1.298.2.dist-info/licenses/SSC-LICENSE
samlib-1.298.2.dist-info/RECORD
