Metadata-Version: 2.4
Name: samlib
Version: 1.298.2
Summary: High-level library for NREL's SAM Simulation Core (SSC)
Project-URL: Source Code, https://github.com/avantus-tech/samlib
Author-email: Brandon Carpenter <brandon@avantus.com>
License-Expression: BSD-3-Clause
License-File: LICENSE
License-File: SSC-LICENSE
Keywords: NREL,SAM,SSC,System Advisor Model,model,techno-economic
Classifier: Development Status :: 5 - Production/Stable
Classifier: Intended Audience :: Developers
Classifier: Intended Audience :: Science/Research
Classifier: License :: OSI Approved :: BSD License
Classifier: Operating System :: MacOS
Classifier: Operating System :: Microsoft :: Windows
Classifier: Operating System :: POSIX :: Linux
Classifier: Programming Language :: Python :: 3.10
Classifier: Programming Language :: Python :: 3.11
Classifier: Programming Language :: Python :: 3.12
Classifier: Programming Language :: Python :: 3.13
Classifier: Programming Language :: Python :: Implementation :: CPython
Classifier: Topic :: Scientific/Engineering
Classifier: Typing :: Typed
Requires-Python: >=3.10
